cloud_cache/__init__.py
venv/bin/activate_this.py
venv/bin/rst2html.py
venv/bin/rst2html4.py
venv/bin/rst2html5.py
venv/bin/rst2latex.py
venv/bin/rst2man.py
venv/bin/rst2odt.py
venv/bin/rst2odt_prepstyles.py
venv/bin/rst2pseudoxml.py
venv/bin/rst2s5.py
venv/bin/rst2xetex.py
venv/bin/rst2xml.py
venv/bin/rstpep2html.py
cloud_cache-0.0.1.dist-info/METADATA
cloud_cache-0.0.1.dist-info/WHEEL
cloud_cache-0.0.1.dist-info/top_level.txt
cloud_cache-0.0.1.dist-info/RECORD
