Metadata-Version: 2.1
Name: cloud-cache
Version: 0.0.1
Summary: emty public cloud_cache
Author-email: voyager18 <research@vulcancyber.io>
Classifier: Programming Language :: Python :: 3
Classifier: Operating System :: OS Independent
Requires-Python: >=3.7
